pwbs/__init__.py
pwbs/__main__.py
pwbs/pwbs_class.py
pwbs/api/__init__.py
pwbs/api/event_manager.py
pwbs/api/plugin.py
pwbs/api/plugin_event_manager.py
pwbs/api/pwbs_event_manager.py
pwbs/command/__init__.py
pwbs/command/command.py
pwbs/config/__init__.py
pwbs/config/config_manager.py
pwbs/config/pwbs_config.py
pwbs/core/__init__.py
pwbs/lib/__init__.py
pwbs/lib/singleton.py
pwbs/lib/pwm/__init__.py
pwbs/lib/pwm/pwm_debug.py
pwbs/lib/pwm/pwm_exec.py
pwbs/lib/pwm/pwm_json.py
pwbs/lib/pwm/pwm_system.py
pwbs/lib/pwm/pwm_watcher.py
pwbs/log/__init__.py
pwbs/log/logger.py
pwbs/tests/TTTTTT_test_6.py
pwbs/tests/__init__.py
pwbs/tests/test_0.py
pwbs/tests/test_1.py
pwbs/tests/test_2.py
pwbs/tests/test_3.py
pwbs/tests/test_5.py
pwbs-0.5.0.dev2.dist-info/AUTHORS.rst
pwbs-0.5.0.dev2.dist-info/LICENSE
pwbs-0.5.0.dev2.dist-info/METADATA
pwbs-0.5.0.dev2.dist-info/WHEEL
pwbs-0.5.0.dev2.dist-info/entry_points.txt
pwbs-0.5.0.dev2.dist-info/top_level.txt
pwbs-0.5.0.dev2.dist-info/RECORD
